rightmove_webscraper/__init__.py
rightmove_webscraper/scraper.py
rightmove_webscraper-1.1.2.dist-info/LICENSE
rightmove_webscraper-1.1.2.dist-info/METADATA
rightmove_webscraper-1.1.2.dist-info/WHEEL
rightmove_webscraper-1.1.2.dist-info/top_level.txt
rightmove_webscraper-1.1.2.dist-info/RECORD
