Metadata-Version: 2.1
Name: rightmove-webscraper
Version: 1.1.2
Summary: A class for scraping data from rightmove.co.uk
Home-page: https://github.com/toby-p/rightmove_webscraper.py
Author: Toby Petty
Author-email: toby.b.petty@gmail.com
License: MIT
Keywords: webscraping,rightmove,data
Platform: UNKNOWN
Classifier: Development Status :: 5 - Production/Stable
Classifier: Intended Audience :: End Users/Desktop
Classifier: License :: OSI Approved :: MIT License
Classifier: Programming Language :: Python :: 3.6
Requires-Python: >=3.6
License-File: LICENSE
Requires-Dist: lxml (>=4.8.0)
Requires-Dist: numpy (>=1.22.3)
Requires-Dist: pandas (>=1.4.1)
Requires-Dist: requests (>=2.27.1)
